README.md
setup.py
pyutils_v3.egg-info/PKG-INFO
pyutils_v3.egg-info/SOURCES.txt
pyutils_v3.egg-info/dependency_links.txt
pyutils_v3.egg-info/requires.txt
pyutils_v3.egg-info/top_level.txt
utils_v3/__init__.py
utils_v3/get_stats.py