Metadata-Version: 2.1
Name: pyutils-v3
Version: 0.1
Summary: A handy library inspired by kaldi/egs/wsj/utils
Home-page: https://github.com/lamnguyen95/pyutils_v3
Author: Lam Nguyen
Author-email: lamfm95@gmail.com
License: UNKNOWN
Platform: UNKNOWN
Classifier: Programming Language :: Python :: 3
Classifier: License :: OSI Approved :: MIT License
Classifier: Operating System :: OS Independent
Requires-Python: >=3.7
